RFM69/__init__.py
RFM69/config.py
RFM69/packet.py
RFM69/radio.py
RFM69/registers.py
rpi_rfm69-0.7.0.dist-info/LICENSE
rpi_rfm69-0.7.0.dist-info/METADATA
rpi_rfm69-0.7.0.dist-info/WHEEL
rpi_rfm69-0.7.0.dist-info/top_level.txt
rpi_rfm69-0.7.0.dist-info/RECORD
