Metadata-Version: 2.1
Name: rpi-rfm69
Version: 0.7.0
Summary: RFM69 Radio interface for the Raspberry Pi
Home-page: https://github.com/jgillula/rpi-rfm69
Author: Jeremy Gillula
Author-email: jgillula+rfm69rpi@gmail.com
License: UNKNOWN
Project-URL: Bug Reports, https://github.com/jgillula/rpi-rfm69/issues
Project-URL: Source, https://github.com/jgillula/rpi-rfm69/issues
Project-URL: Documentation, http://rpi-rfm69.readthedocs.io/
Project-URL: Tracker, https://github.com/jgillula/rpi-rfm69/issues
Keywords: rfm69 raspberry pi rf69 radio rfm69cw rfm69hcw
Platform: UNKNOWN
Classifier: Development Status :: 4 - Beta
Classifier: Intended Audience :: Developers
Classifier: Topic :: Communications
Classifier: License :: OSI Approved :: GNU General Public License v3 (GPLv3)
Classifier: Programming Language :: Python :: 3
License-File: LICENSE
Requires-Dist: spidev
Requires-Dist: RPI.GPIO
